{
  "$schema": "https://raw.githubusercontent.com/getmanfred/mac/v0.3/schema/schema.json",
  "settings": {
    "language": "ES",
    "MACVersion": "0.3"
  },
  "aboutMe": {
    "profile": {
      "name": "José María",
      "surnames": "Moreno Terrén",
      "title": "Desarrollador Full Stack",
      "description": "Soy un apasionado del desarrollo de software, al cual llevo dedicado toda mi vida, disfruto desarrollando software y creando aplicaciones, es mi pasión además de mi profesión. También soy un gran aficionado al submarinismo, suelo jugar al fútbol (intento evitar que mis hijos me vean) y me gusta tocar la batería. Ah, y patrón de embarcaciones de recreo sin barco, que se le va a hacer.\n\nTengo una dilatadísima experiencia profesional en el mundo de la informática (no exagero, son 28 años cotizados a la seguridad social en el sector, ¡qué vértigo!), dedicados tanto al desarrollo frontend como backend, al desarrollo de aplicaciones móviles y en la implantación y desarrollo de ERPs, CRMs y comercio electrónico. Aunque no tengo la carrera he realizado multitud de cursos y he adquirido conocimientos de un amplio número de herramientas y tecnológicas, le invito a que ojee mi perfil de Linkedin donde podrá encontrar un amplio detalle así como algunas referencias interesantes. ",
      "location": {
        "country": "España",
        "region": "Andalucía",
        "municipality": "Motril",
        "notes": "Autocompleted using Google Maps API"
      }
    },
    "relevantLinks": [
      {
        "type": "linkedin",
        "URL": "https://www.linkedin.com/in/jose-maria-moreno/"
      }
    ],
    "interestingFacts": [
      {
        "topic": "Otras actividades",
        "fact": "La práctica del fútbol entre amigos, el submarinismo y tocar la batería son mis principales aficiones, las cuales practico con bastante frecuencia."
      }
    ]
  },
  "experience": {
    "jobs": [
      {
        "organization": {
          "name": "Ériddes Informática Industrial, S.L.",
          "image": {
            "alt": "logo_eriddes_p.fw.png",
            "link": "https://media-asgard.s3.eu-west-1.amazonaws.com/23/04/03/d33ecdad-2231-426d-9fea-d173e1044f3e_logo_eriddes_p.png"
          }
        },
        "roles": [
          {
            "name": "Desarrollador Full Stack",
            "startDate": "2017-06-01",
            "challenges": [
              {
                "description": "Desarrollo de aplicaciones móviles con Ionic o Electron, SPA web con HTML5/CSS/Javascript y API Rest con Node.JS, Express, PostgreSQL y MongoDB, desplegadas tanto en local o como en Cloud con Heroku.\nDesarrollo y publicación de Apps en Google Play y App Store.\nDesarrollo de Soluciones de análisis de negocio con QlikView."
              }
            ],
            "competences": [
              {
                "name": "Angular2+",
                "type": "technology"
              },
              {
                "name": "Express",
                "type": "technology"
              },
              {
                "name": "HTML",
                "type": "technology"
              },
              {
                "name": "Ionic",
                "type": "technology"
              },
              {
                "name": "MongoDB",
                "type": "technology"
              },
              {
                "name": "NodeJS",
                "type": "technology"
              },
              {
                "name": "PostgreSQL",
                "type": "technology"
              },
              {
                "name": "Scss",
                "type": "technology"
              }
            ]
          }
        ]
      },
      {
        "organization": {
          "name": "DANTIA Tecnología",
          "image": {
            "alt": "Sin título.png",
            "link": "https://media-asgard.s3.eu-west-1.amazonaws.com/23/04/03/e1903778-70a2-4061-9836-03a7d7787288_sin-titulo.png"
          },
          "URL": "https://www.dantia.es"
        },
        "roles": [
          {
            "name": "Consultor ERP/CRM e integrador de sistemas",
            "startDate": "2011-10-01",
            "finishDate": "2017-07-01",
            "challenges": [
              {
                "description": "Consultoría e implantación de soluciones de gestión empresarial ERP y CRM, integración con sistemas de comercio electrónico. Técnico preventa."
              }
            ],
            "competences": [
              {
                "name": "Magento",
                "type": "technology"
              },
              {
                "name": "MySQL",
                "type": "technology"
              },
              {
                "name": "PHP",
                "type": "technology"
              },
              {
                "name": "SQLServer",
                "type": "technology"
              },
              {
                "name": "VB.NET",
                "type": "technology"
              }
            ]
          }
        ]
      }
    ]
  },
  "knowledge": {
    "languages": [
      {
        "name": "English",
        "level": "Full professional proficiency"
      }
    ],
    "hardSkills": [
      {
        "skill": {
          "name": "Ionic",
          "type": "technology"
        }
      },
      {
        "skill": {
          "name": "Angular2+",
          "type": "technology"
        }
      },
      {
        "skill": {
          "name": "MongoDB",
          "type": "technology"
        }
      },
      {
        "skill": {
          "name": "Magento",
          "type": "technology"
        }
      },
      {
        "skill": {
          "name": "PostgreSQL",
          "type": "technology"
        }
      },
      {
        "skill": {
          "name": "Express",
          "type": "technology"
        }
      },
      {
        "skill": {
          "name": "Cypress",
          "type": "technology"
        }
      },
      {
        "skill": {
          "name": "Mocha",
          "type": "technology"
        }
      },
      {
        "skill": {
          "name": "Shopify",
          "type": "technology"
        }
      },
      {
        "skill": {
          "name": "TypeScript",
          "type": "technology"
        }
      },
      {
        "skill": {
          "name": "Heroku",
          "type": "technology"
        }
      },
      {
        "skill": {
          "name": "PHP",
          "type": "technology"
        }
      },
      {
        "skill": {
          "name": "Kafka",
          "type": "technology"
        }
      },
      {
        "skill": {
          "name": "MySQL",
          "type": "technology"
        }
      },
      {
        "skill": {
          "name": "React",
          "type": "technology"
        }
      },
      {
        "skill": {
          "name": "SQLServer",
          "type": "technology"
        }
      },
      {
        "skill": {
          "name": "Vue",
          "type": "technology"
        }
      },
      {
        "skill": {
          "name": "Qlik",
          "type": "technology"
        }
      },
      {
        "skill": {
          "name": "Bootstrap",
          "type": "technology"
        }
      },
      {
        "skill": {
          "name": "Python",
          "type": "technology"
        }
      },
      {
        "skill": {
          "name": "Mongoose",
          "type": "technology"
        }
      },
      {
        "skill": {
          "name": "Prestashop",
          "type": "technology"
        }
      }
    ],
    "studies": [
      {
        "studyType": "certification",
        "degreeAchieved": true,
        "name": "Desarrollador certificado Velneo 2023",
        "startDate": "2022-12-01",
        "finishDate": "2023-12-01",
        "institution": {
          "name": "Velneo",
          "description": "Cada año me examino para renovar la certificación como desarrollador Velneo, que conozco aunque no es la principal herramienta de trabajo.",
          "URL": "https://velneo.es/mivelneo/desarrolladores-certificados-velneo/",
          "image": {
            "alt": "sello H - 2023.png",
            "link": "https://media-asgard.s3.eu-west-1.amazonaws.com/23/04/02/7ccb0ef9-3672-4097-ac33-30fa99e9e547_sello-h---2023.png"
          }
        }
      }
    ]
  },
  "careerPreferences": {
    "contact": {
      "publicProfiles": [
        {
          "type": "linkedin",
          "URL": "https://www.linkedin.com/in/jose-maria-moreno/"
        }
      ]
    },
    "preferences": {
      "preferredCompetences": [
        {
          "name": "Angular2+",
          "type": "technology"
        },
        {
          "name": "Docker",
          "type": "technology"
        },
        {
          "name": "Heroku",
          "type": "technology"
        },
        {
          "name": "Ionic",
          "type": "technology"
        },
        {
          "name": "Kubernetes",
          "type": "technology"
        },
        {
          "name": "MongoDB",
          "type": "technology"
        },
        {
          "name": "NodeJS",
          "type": "technology"
        }
      ],
      "preferredRoles": [
        "Backend Developer",
        "Data Analysis & BI",
        "Developer Evangelist & Advocate",
        "Frontend Developer",
        "Full-stack Developer",
        "Lead Product Manager",
        "Mobile Developer",
        "Product Analyst",
        "Product Design (UI/UX)",
        "Product Manager",
        "QA & Testing Engineer",
        "Software Architect",
        "Tech Lead"
      ]
    },
    "status": "searchingActively"
  }
}